blsl/__init__.py
blsl/__main__.py
blsl/_utils.py
blsl/deepclust2fa.py
blsl/ebiosra2rl2s.py
blsl/equalbestblast.py
blsl/esearchandfetch.py
blsl/falen.py
blsl/farename.py
blsl/fastasanitiser.py
blsl/fqstat.py
blsl/galhist.py
blsl/genebed.py
blsl/genigvjs.py
blsl/gffcat.py
blsl/gffcsqify.py
blsl/gffparse.py
blsl/gfftagsane.py
blsl/gg2k.py
blsl/ildemux.py
blsl/ilsample.py
blsl/jsonl2csv.py
blsl/liftoff_gff3.py
blsl/mask2bed.py
blsl/n50.py
blsl/nstitch.py
blsl/pairs.py
blsl/pairslash.py
blsl/pansn_rename.py
blsl/regionbed.py
blsl/shannon.py
blsl/tabcat.py
blsl/telogrep.py
blsl/tidyqc.py
blsl/uniref_accessionmap.py
blsl/vcfparallel.py
blsl/vcfreport.py
blsl/vcfstats.py
blindschleiche-0.4.4.dist-info/entry_points.txt
blindschleiche-0.4.4.dist-info/WHEEL
blindschleiche-0.4.4.dist-info/METADATA
blindschleiche-0.4.4.dist-info/RECORD
