Metadata-Version: 2.1
Name: blindschleiche
Version: 0.4.4
Summary: Miscelanelous python-based bioinformatics utils
Author-email: "Dr. K. D. Murray" <info@gekkonid.com>
Requires-Python: >=3.8
Requires-Dist: tqdm
Requires-Dist: biopython
Requires-Dist: cyvcf2
Requires-Dist: pandas
Requires-Dist: scikit-learn
Requires-Dist: physt
Requires-Dist: plotly
